assinstants/__init__.py
assinstants/_version.py
assinstants/py.typed
assinstants/core/__init__.py
assinstants/core/assistant_manager.py
assinstants/core/run_manager.py
assinstants/core/thread_manager.py
assinstants/models/__init__.py
assinstants/models/assistant.py
assinstants/models/base.py
assinstants/models/function.py
assinstants/models/message.py
assinstants/models/run.py
assinstants/models/shared.py
assinstants/models/thread.py
assinstants/models/tool.py
assinstants/utils/__init__.py
assinstants/utils/exceptions.py
assinstants/utils/logging_utils.py
assinstants-1.1.6.dist-info/METADATA
assinstants-1.1.6.dist-info/WHEEL
assinstants-1.1.6.dist-info/top_level.txt
assinstants-1.1.6.dist-info/RECORD
