Metadata-Version: 2.1
Name: assinstants
Version: 1.1.6
Summary: A framework for managing AI assistants
Home-page: https://github.com/lahfir/assinstants
Author: Lahfir
Author-email: nmhlahfir2@gmail.com
Classifier: Development Status :: 3 - Alpha
Classifier: Intended Audience :: Developers
Classifier: License :: OSI Approved :: MIT License
Classifier: Operating System :: OS Independent
Classifier: Programming Language :: Python :: 3
Classifier: Programming Language :: Python :: 3.7
Classifier: Programming Language :: Python :: 3.8
Classifier: Programming Language :: Python :: 3.9
Classifier: Programming Language :: Python :: 3.10
Classifier: Typing :: Typed
Requires-Python: >=3.7
Requires-Dist: aiohttp
Requires-Dist: pydantic >=2.0.0
Requires-Dist: colorama
Requires-Dist: setuptools-scm
